pykmertools-0.2.1.dist-info/METADATA
pykmertools-0.2.1.dist-info/WHEEL
pykmertools-0.2.1.dist-info/entry_points.txt
pykmertools-0.2.1.dist-info/licenses/LICENSE
pykmertools/__init__.py
pykmertools/__init__.pyi
pykmertools/py.typed
pykmertools/pykmertools.pyd
pykmertools-0.2.1.dist-info/RECORD
