Metadata-Version: 2.4
Name: pykmertools
Version: 0.2.1
Classifier: Programming Language :: Rust
Classifier: Programming Language :: Python :: Implementation :: CPython
Classifier: Programming Language :: Python :: Implementation :: PyPy
License-File: LICENSE
Summary: kmertools is a k-mer based feature extraction tool designed to support metagenomics and other bioinformatics analytics.
Keywords: genomics,bioinformatics
Requires-Python: >=3.9
Project-URL: Documentation, https://github.com/anuradhawick/kmertools/wiki
Project-URL: Bug Tracker, https://github.com/anuradhawick/kmertools/issues
Project-URL: Source Code, https://github.com/anuradhawick/kmertools/
